{"_type":"export","__export_format":4,"__export_date":"2021-10-01T07:26:17.667Z","__export_source":"insomnia.desktop.app:v2021.5.3","resources":[{"_id":"req_f85923df3b874c43aaf4b3f940266d52","parentId":"wrk_8ed9b868ab1f432fb20376a86ec099ad","modified":1633073145651,"created":1633072779868,"url":"http://localhost:28017/api/workouts/6156a4b7e65e9d4990988a03","name":"Add Exercise(cardio) to Workout","description":"","method":"PUT","body":{"mimeType":"application/json","text":"{\n\t\"type\":\"cardio\",\n\t\"name\":\"A test run\",\n\t\"duration\":30,\n\t\"distance\":20\n}"},"parameters":[],"headers":[{"name":"Content-Type","value":"application/json","id":"pair_7ef12e0868124962b6023c6a15d6d6ab"}],"authentication":{},"metaSortKey":-1633072779868,"isPrivate":false,"settingStoreCookies":true,"settingSendCookies":true,"settingDisableRenderRequestBody":false,"settingEncodeUrl":true,"settingRebuildPath":true,"settingFollowRedirects":"global","_type":"request"},{"_id":"wrk_8ed9b868ab1f432fb20376a86ec099ad","parentId":null,"modified":1633069801845,"created":1633069801845,"name":"Fitness Tracker","description":"","scope":"collection","_type":"workspace"},{"_id":"req_56b1e8978d404f569fa21c43c676d0bb","parentId":"wrk_8ed9b868ab1f432fb20376a86ec099ad","modified":1633073139314,"created":1633073100775,"url":"http://localhost:28017/api/workouts/6156a4b7e65e9d4990988a03","name":"Add Exercise(resistance) to Workout","description":"","method":"PUT","body":{"mimeType":"application/json","text":"{\n\t\"type\":\"resistance\",\n\t\"name\":\"A test run\",\n\t\"duration\":30,\n\t\"weight\":120,\n\t\"reps\":6,\n\t\"sets\":10\n}"},"parameters":[],"headers":[{"name":"Content-Type","value":"application/json","id":"pair_7ef12e0868124962b6023c6a15d6d6ab"}],"authentication":{},"metaSortKey":-1633072707708,"isPrivate":false,"settingStoreCookies":true,"settingSendCookies":true,"settingDisableRenderRequestBody":false,"settingEncodeUrl":true,"settingRebuildPath":true,"settingFollowRedirects":"global","_type":"request"},{"_id":"req_0549936c6bf3467b9b98ceacbcd0fa8a","parentId":"wrk_8ed9b868ab1f432fb20376a86ec099ad","modified":1633072650095,"created":1633072635548,"url":"http://localhost:28017/stats","name":"Get Stats Page","description":"","method":"GET","body":{},"parameters":[],"headers":[],"authentication":{},"metaSortKey":-1633072635548,"isPrivate":false,"settingStoreCookies":true,"settingSendCookies":true,"settingDisableRenderRequestBody":false,"settingEncodeUrl":true,"settingRebuildPath":true,"settingFollowRedirects":"global","_type":"request"},{"_id":"req_7a8dfc16059348dbaac9badf863fc91c","parentId":"wrk_8ed9b868ab1f432fb20376a86ec099ad","modified":1633072700062,"created":1633072614621,"url":"http://localhost:28017/api/workouts","name":"Create Workout","description":"","method":"POST","body":{},"parameters":[],"headers":[],"authentication":{},"metaSortKey":-1633072614621,"isPrivate":false,"settingStoreCookies":true,"settingSendCookies":true,"settingDisableRenderRequestBody":false,"settingEncodeUrl":true,"settingRebuildPath":true,"settingFollowRedirects":"global","_type":"request"},{"_id":"req_11285f3ae4984fd39e3a8d26024279af","parentId":"wrk_8ed9b868ab1f432fb20376a86ec099ad","modified":1633072560139,"created":1633072530940,"url":"http://localhost:28017/api/workouts","name":"Get All Workouts","description":"","method":"GET","body":{},"parameters":[],"headers":[],"authentication":{},"metaSortKey":-1633072530940,"isPrivate":false,"settingStoreCookies":true,"settingSendCookies":true,"settingDisableRenderRequestBody":false,"settingEncodeUrl":true,"settingRebuildPath":true,"settingFollowRedirects":"global","_type":"request"},{"_id":"req_e9036b1781d44579b31e5ec3df66f728","parentId":"wrk_8ed9b868ab1f432fb20376a86ec099ad","modified":1633072643183,"created":1633069823291,"url":"http://localhost:28017/","name":"Get Home page","description":"","method":"GET","body":{},"parameters":[],"headers":[],"authentication":{},"metaSortKey":-1633069823292,"isPrivate":false,"settingStoreCookies":true,"settingSendCookies":true,"settingDisableRenderRequestBody":false,"settingEncodeUrl":true,"settingRebuildPath":true,"settingFollowRedirects":"global","_type":"request"},{"_id":"env_5e59223606e8b1eb00fc90a6cba54f43e4e04c82","parentId":"wrk_8ed9b868ab1f432fb20376a86ec099ad","modified":1633069801851,"created":1633069801851,"name":"Base Environment","data":{},"dataPropertyOrder":null,"color":null,"isPrivate":false,"metaSortKey":1633069801851,"_type":"environment"},{"_id":"jar_5e59223606e8b1eb00fc90a6cba54f43e4e04c82","parentId":"wrk_8ed9b868ab1f432fb20376a86ec099ad","modified":1633069801853,"created":1633069801853,"name":"Default Jar","cookies":[],"_type":"cookie_jar"},{"_id":"spc_e9c3d04112a34d21adb502dac706d97e","parentId":"wrk_8ed9b868ab1f432fb20376a86ec099ad","modified":1633069801847,"created":1633069801847,"fileName":"Fitness Tracker","contents":"","contentType":"yaml","_type":"api_spec"}]}